requests_wrapper/__init__.py
requests_wrapper/api_key_tracker.py
requests_wrapper/requests_wrapper.py
requests_wrapper-0.0.3.dist-info/LICENSE
requests_wrapper-0.0.3.dist-info/METADATA
requests_wrapper-0.0.3.dist-info/WHEEL
requests_wrapper-0.0.3.dist-info/top_level.txt
requests_wrapper-0.0.3.dist-info/RECORD
