Metadata-Version: 2.1
Name: requests-wrapper
Version: 0.0.3
Summary: Wrapper around requests package, with extra API key management
Home-page: https://github.com/chilledgeek/requests-wrapper
Author: E CHOW
Author-email: chilledgeek@gmail.com
License: MIT
Platform: UNKNOWN
Classifier: License :: OSI Approved :: MIT License
Classifier: Programming Language :: Python
Classifier: Programming Language :: Python :: 3
Requires-Dist: requests
